{"skeleton":{"hash":"VBPvujx8/WM","spine":"4.2.36","x":-400,"y":-398,"width":800,"height":796,"images":"./image/","audio":"./audio"},"bones":[{"name":"root"},{"name":"BG_Room","parent":"root"},{"name":"icon 1","parent":"root"}],"slots":[{"name":"BG_Room","bone":"BG_Room","attachment":"BG_Room"},{"name":"icon 1","bone":"icon 1","attachment":"icon"}],"skins":[{"name":"Icon_1","attachments":{"icon 1":{"icon":{"name":"icon 1","width":800,"height":796}}}},{"name":"Icon_2","attachments":{"icon 1":{"icon":{"name":"icon 2","width":800,"height":796}}}},{"name":"Icon_3","attachments":{"icon 1":{"icon":{"name":"icon 3","width":800,"height":796}}}},{"name":"Icon_4","attachments":{"icon 1":{"icon":{"name":"icon 4","width":800,"height":796}}}},{"name":"Icon_5","attachments":{"icon 1":{"icon":{"name":"icon 5","width":800,"height":796}}}},{"name":"Icon_6","attachments":{"icon 1":{"icon":{"name":"icon 6","width":800,"height":796}}}},{"name":"Skin_1","attachments":{"BG_Room":{"BG_Room":{"width":1103,"height":1809}}}},{"name":"Skin_2","attachments":{"BG_Room":{"BG_Room":{"name":"BG_Room_02","width":1103,"height":1809}}}},{"name":"Skin_3","attachments":{"BG_Room":{"BG_Room":{"name":"BG_Room_03","width":1103,"height":1809}}}},{"name":"Skin_4","attachments":{"BG_Room":{"BG_Room":{"name":"BG_Room_04","width":1103,"height":1809}}}},{"name":"Skin_5","attachments":{"BG_Room":{"BG_Room":{"name":"BG_Room_05","width":1103,"height":1809}}}},{"name":"Skin_6","attachments":{"BG_Room":{"BG_Room":{"name":"BG_Room_06","width":1101,"height":1809}}}}],"animations":{"Idle":{}}}